quixstreams_extensions/__init__.py
quixstreams_extensions/serializers/__init__.py
quixstreams_extensions/serializers/composer.py
quixstreams_extensions/serializers/compositions/__init__.py
quixstreams_extensions/serializers/compositions/confluent.py
quixstreams_extensions/serializers/compositions/pydantic.py
quixstreams_extensions/sinks/__init__.py
quixstreams_extensions/sinks/google_cloud.py
quixstreams_extensions-0.2.1.dist-info/LICENSE
quixstreams_extensions-0.2.1.dist-info/METADATA
quixstreams_extensions-0.2.1.dist-info/WHEEL
quixstreams_extensions-0.2.1.dist-info/RECORD
