Metadata-Version: 2.1
Name: quixstreams-extensions
Version: 0.2.1
Summary: Extends quix-streams functionality
License: Apache 2.0
Author: Volodymyr
Author-email: trotsyshyn@proton.me
Requires-Python: >=3.9,<4.0
Classifier: License :: Other/Proprietary License
Classifier: Programming Language :: Python :: 3
Classifier: Programming Language :: Python :: 3.9
Classifier: Programming Language :: Python :: 3.10
Classifier: Programming Language :: Python :: 3.11
Classifier: Programming Language :: Python :: 3.12
Provides-Extra: avro
Provides-Extra: gcp
Provides-Extra: pydantic
Requires-Dist: orjson (<=3.10.6)
Requires-Dist: quixstreams (>=2.9.0,<3.0.0)
Project-URL: Homepage, https://github.com/devova/quix-streams-extensions
